[
  {
    "record_id": "1747",
    "Cantiere": "Cantiere di restauro: I stralcio - Messa di sicurezza dei locali di proprietà della Provincia dati in comodato ad Alma, Architettonico",
    "zone/subject_raw": "Restauro dei paramenti esterni",
    "Date": "2013-04-01 00:00:00",
    "Author": "Buia Nereo S.r.l.",
    "supporto": "",
    "zone": [],
    "materials_used": [],
    "technique_used": [
      "Rimozione di depositi, scialbature o vernici"
    ],
    "environmental_issue": [],
    "working_issue": [],
    "observations": [
      "Operazione di rimozione dell'intonaco esistente."
    ]
  },
  {
    "record_id": "1747",
    "Cantiere": "Cantiere di restauro: I stralcio - Messa di sicurezza dei locali di proprietà della Provincia dati in comodato ad Alma, Architettonico",
    "zone/subject_raw": "Restauro dei paramenti esterni",
    "Date": "2013-04-01 00:00:00",
    "Author": "Buia Nereo S.r.l.",
    "supporto": "Architettonico",
    "zone": [],
    "materials_used": [
      "Resine epossidiche (Araldite, Sikadur, Epox)"
    ],
    "technique_used": [],
    "environmental_issue": [],
    "working_issue": [],
    "observations": [
      "Stesura a rullo di resina tipo Sikadur 330."
    ]
  },
  {
    "record_id": "1747",
    "Cantiere": "Cantiere di restauro: I stralcio - Messa di sicurezza dei locali di proprietà della Provincia dati in comodato ad Alma, Architettonico",
    "zone/subject_raw": "Restauro dei paramenti esterni",
    "Date": "2013-04-01 00:00:00",
    "Author": "Buia Nereo S.r.l.",
    "supporto": "Architettonico",
    "zone": [],
    "materials_used": [
      "Fibre e compositi (fibra di vetro, carbonio, vetroresina)"
    ],
    "technique_used": [],
    "environmental_issue": [],
    "working_issue": [],
    "observations": [
      "Si è registrato l'uso di tessuto in fibra di carbonio per posa."
    ]
  },
  {
    "record_id": "1747",
    "Cantiere": "Cantiere di restauro: I stralcio - Messa di sicurezza dei locali di proprietà della Provincia dati in comodato ad Alma, Architettonico",
    "zone/subject_raw": "Restauro dei paramenti esterni",
    "Date": "2013-04-01 00:00:00",
    "Author": "Buia Nereo S.r.l.",
    "supporto": "Architettonico",
    "zone": [
      "Murature",
      "Pavimenti/Solai"
    ],
    "materials_used": [
      "Inerti e sabbie",
      "Malte cementizie"
    ],
    "technique_used": [
      "Interventi su intonaci (intonacatura / reintonacatura)"
    ],
    "environmental_issue": [],
    "working_issue": [],
    "observations": [
      "Applicazione di sabbia seguita dall'applicazione di un nuovo intonaco."
    ]
  },
  {
    "record_id": "1747",
    "Cantiere": "Cantiere di restauro: I stralcio - Messa di sicurezza dei locali di proprietà della Provincia dati in comodato ad Alma, Architettonico",
    "zone/subject_raw": "Restauro dei paramenti esterni",
    "Date": "2013-04-01 00:00:00",
    "Author": "Buia Nereo S.r.l.",
    "supporto": "Architettonico",
    "zone": [],
    "materials_used": [],
    "technique_used": [
      "Indagini diagnostiche e analisi preliminari",
      "Pulitura meccanica"
    ],
    "environmental_issue": [],
    "working_issue": [
      "Difficoltà operative e accessibilità (quota, posizionamento, intervento diretto)"
    ],
    "observations": [
      "Lavori focalizzati sullo smontaggio e riposizionamento di elementi metallici."
    ]
  },
  {
    "record_id": "1747",
    "Cantiere": "Cantiere di restauro: I stralcio - Messa di sicurezza dei locali di proprietà della Provincia dati in comodato ad Alma, Architettonico",
    "zone/subject_raw": "Restauro dei paramenti esterni",
    "Date": "2013-04-01 00:00:00",
    "Author": "Buia Nereo S.r.l.",
    "supporto": "Murario",
    "zone": [
      "Murature"
    ],
    "materials_used": [
      "Biocidi/antimuffa/antivegetativi"
    ],
    "technique_used": [
      "Trattamenti biocidi / disinfestazione"
    ],
    "environmental_issue": [
      "attacchi biologici (licheni)"
    ],
    "working_issue": [],
    "observations": [
      "Lavori di eliminazione della vegetazione e trattamento con biocida"
    ]
  },
  {
    "record_id": "1747",
    "Cantiere": "Cantiere di restauro: I stralcio - Messa di sicurezza dei locali di proprietà della Provincia dati in comodato ad Alma, Architettonico",
    "zone/subject_raw": "Restauro dei paramenti esterni",
    "Date": "2013-04-01 00:00:00",
    "Author": "Buia Nereo S.r.l.",
    "supporto": "Architettonico",
    "zone": [],
    "materials_used": [
      "Calce (grassello, calce dolce, calce storica)",
      "Inerti e sabbie",
      "Cariche minerali (carbonato di calcio, polveri di pietra/marmo/travertino)"
    ],
    "technique_used": [],
    "environmental_issue": [],
    "working_issue": [],
    "observations": [
      "Riparazione di lesioni isolate con materiali leganti di calce e sabbia fine o polvere di marmo."
    ]
  },
  {
    "record_id": "1747",
    "Cantiere": "Cantiere di restauro: I stralcio - Messa di sicurezza dei locali di proprietà della Provincia dati in comodato ad Alma, Architettonico",
    "zone/subject_raw": "Restauro dei paramenti esterni",
    "Date": "2013-04-01 00:00:00",
    "Author": "Buia Nereo S.r.l.",
    "supporto": "Architettonico",
    "zone": [],
    "materials_used": [],
    "technique_used": [
      "Rimozione di depositi, scialbature o vernici",
      "Pulitura meccanica"
    ],
    "environmental_issue": [],
    "working_issue": [],
    "observations": [
      "Rimozione di materiale incoerente e pulitura delle superfici effettuate per preparare le successive fasi di consolidamento."
    ]
  },
  {
    "record_id": "1747",
    "Cantiere": "Cantiere di restauro: I stralcio - Messa di sicurezza dei locali di proprietà della Provincia dati in comodato ad Alma, Architettonico",
    "zone/subject_raw": "Restauro dei paramenti esterni",
    "Date": "2013-04-01 00:00:00",
    "Author": "Buia Nereo S.r.l.",
    "supporto": "Murario",
    "zone": [
      "Murature"
    ],
    "materials_used": [
      "Malte cementizie",
      "Laterizio/cotto/mattoni"
    ],
    "technique_used": [
      "Rimozione di depositi, scialbature o vernici"
    ],
    "environmental_issue": [],
    "working_issue": [
      "Distacco/disancoraggio"
    ],
    "observations": [
      "Demolizione di intonaco distaccato dal supporto murario."
    ]
  },
  {
    "record_id": "1747",
    "Cantiere": "Cantiere di restauro: I stralcio - Messa di sicurezza dei locali di proprietà della Provincia dati in comodato ad Alma, Architettonico",
    "zone/subject_raw": "Restauro dei paramenti esterni",
    "Date": "2013-04-01 00:00:00",
    "Author": "Buia Nereo S.r.l.",
    "supporto": "Architettonico",
    "zone": [
      "Murature",
      "Pavimenti/Solai"
    ],
    "materials_used": [
      "Malte a base calce (premiscelate o tradizionali)",
      "Laterizio/cotto/mattoni"
    ],
    "technique_used": [
      "Interventi su intonaci (intonacatura / reintonacatura)"
    ],
    "environmental_issue": [],
    "working_issue": [],
    "observations": [
      "Fornitura e posa in opera di intonaco civile per interni ed esterni costituito da rinzaffo, abbozzo e ultimo strato eseguito con due strati."
    ]
  },
  {
    "record_id": "1747",
    "Cantiere": "Cantiere di restauro: I stralcio - Messa di sicurezza dei locali di proprietà della Provincia dati in comodato ad Alma, Architettonico",
    "zone/subject_raw": "Restauro dei paramenti esterni",
    "Date": "2013-04-01 00:00:00",
    "Author": "Buia Nereo S.r.l.",
    "supporto": "Murario",
    "zone": [
      "Murature"
    ],
    "materials_used": [
      "Laterizio/cotto/mattoni",
      "Malte a base calce (premiscelate o tradizionali)",
      "Calce (grassello, calce dolce, calce storica)"
    ],
    "technique_used": [
      "Interventi su intonaci (intonacatura / reintonacatura)"
    ],
    "environmental_issue": [],
    "working_issue": [],
    "observations": [
      "Riparazioni di cornici in ossatura di laterizio intonacate."
    ]
  },
  {
    "record_id": "1747",
    "Cantiere": "Cantiere di restauro: I stralcio - Messa di sicurezza dei locali di proprietà della Provincia dati in comodato ad Alma, Architettonico",
    "zone/subject_raw": "Restauro dei paramenti esterni",
    "Date": "2013-04-01 00:00:00",
    "Author": "Buia Nereo S.r.l.",
    "supporto": "Architettonico",
    "zone": [],
    "materials_used": [],
    "technique_used": [
      "Pulitura chimica",
      "Protezione finale / verniciatura"
    ],
    "environmental_issue": [],
    "working_issue": [],
    "observations": [
      "Tinteggiatura effettuata con silicati di potassio per protezione degli esterni."
    ]
  },
  {
    "record_id": "1747",
    "Cantiere": "Cantiere di restauro: I stralcio - Messa di sicurezza dei locali di proprietà della Provincia dati in comodato ad Alma, Architettonico",
    "zone/subject_raw": "",
    "Date": "2013-05-08 00:00:00",
    "Author": "Buia Nereo S.r.l.",
    "supporto": "Architettonico",
    "zone": [],
    "materials_used": [],
    "technique_used": [
      "Rimozione di depositi, scialbature o vernici"
    ],
    "environmental_issue": [],
    "working_issue": [],
    "observations": [
      "L'intervento consiste nella rimozione dell'intonaco esistente."
    ]
  },
  {
    "record_id": "1747",
    "Cantiere": "Cantiere di restauro: I stralcio - Messa di sicurezza dei locali di proprietà della Provincia dati in comodato ad Alma, Architettonico",
    "zone/subject_raw": "",
    "Date": "2013-05-08 00:00:00",
    "Author": "Buia Nereo S.r.l.",
    "supporto": "Architettonico",
    "zone": [],
    "materials_used": [
      "Resine epossidiche (Araldite, Sikadur, Epox)"
    ],
    "technique_used": [],
    "environmental_issue": [],
    "working_issue": [],
    "observations": [
      "Si menziona la stesura di una resina Sikadur330, ma non sono riportati dettagli sull'intervento applicativo o sulla zona interessata."
    ]
  },
  {
    "record_id": "1747",
    "Cantiere": "Cantiere di restauro: I stralcio - Messa di sicurezza dei locali di proprietà della Provincia dati in comodato ad Alma, Architettonico",
    "zone/subject_raw": "",
    "Date": "2013-05-08 00:00:00",
    "Author": "Buia Nereo S.r.l.",
    "supporto": "Architettonico",
    "zone": [],
    "materials_used": [
      "Fibre e compositi (fibra di vetro, carbonio, vetroresina)"
    ],
    "technique_used": [],
    "environmental_issue": [],
    "working_issue": [],
    "observations": [
      "Non sono state fornite informazioni dettagliate sulle zone specifiche trattate, sulle tecniche utilizzate, sugli interventi ambientali o sui problemi operativi."
    ]
  },
  {
    "record_id": "1747",
    "Cantiere": "Cantiere di restauro: I stralcio - Messa di sicurezza dei locali di proprietà della Provincia dati in comodato ad Alma, Architettonico",
    "zone/subject_raw": "",
    "Date": "2013-05-08 00:00:00",
    "Author": "Buia Nereo S.r.l.",
    "supporto": "",
    "zone": [],
    "materials_used": [
      "Inerti e sabbie"
    ],
    "technique_used": [],
    "environmental_issue": [],
    "working_issue": [],
    "observations": [
      "Menzione di stesura di sabbia per migliorare l'aderenza della fibra al supporto."
    ]
  },
  {
    "record_id": "1747",
    "Cantiere": "Cantiere di restauro: I stralcio - Messa di sicurezza dei locali di proprietà della Provincia dati in comodato ad Alma, Architettonico",
    "zone/subject_raw": "",
    "Date": "2013-05-08 00:00:00",
    "Author": "Buia Nereo S.r.l.",
    "supporto": "Architettonico",
    "zone": [
      "Murature",
      "Pavimenti/Solai"
    ],
    "materials_used": [
      "Inerti e sabbie",
      "Malte cementizie"
    ],
    "technique_used": [
      "Interventi su intonaci (intonacatura / reintonacatura)"
    ],
    "environmental_issue": [],
    "working_issue": [],
    "observations": [
      "Rimozione della sabbia e ristesso di un nuovo intonaco effettuati."
    ]
  },
  {
    "record_id": "1747",
    "Cantiere": "Cantiere di restauro: I stralcio - Messa di sicurezza dei locali di proprietà della Provincia dati in comodato ad Alma, Architettonico",
    "zone/subject_raw": "",
    "Date": "2013-05-03 00:00:00",
    "Author": "Buia Nereo S.r.l.",
    "supporto": "Murario",
    "zone": [],
    "materials_used": [
      "Laterizio/cotto/mattoni"
    ],
    "technique_used": [
      "Indagini diagnostiche e analisi preliminari"
    ],
    "environmental_issue": [],
    "working_issue": [
      "Difficoltà operative e accessibilità (quota, posizionamento, intervento diretto)"
    ],
    "observations": [
      "Smontaggio e accatastamento del materiale effettuati."
    ]
  },
  {
    "record_id": "1747",
    "Cantiere": "Cantiere di restauro: I stralcio - Messa di sicurezza dei locali di proprietà della Provincia dati in comodato ad Alma, Architettonico",
    "zone/subject_raw": "",
    "Date": "2013-05-03 00:00:00",
    "Author": "Buia Nereo S.r.l.",
    "supporto": "Architettonico",
    "zone": [],
    "materials_used": [],
    "technique_used": [
      "Pulitura meccanica"
    ],
    "environmental_issue": [],
    "working_issue": [],
    "observations": [
      "La pulitura è stata effettuata con strumenti manuali come spazzole e mazzuolo per rimuovere le malte in eccesso."
    ]
  },
  {
    "record_id": "1747",
    "Cantiere": "Cantiere di restauro: I stralcio - Messa di sicurezza dei locali di proprietà della Provincia dati in comodato ad Alma, Architettonico",
    "zone/subject_raw": "",
    "Date": "2013-05-03 00:00:00",
    "Author": "Buia Nereo S.r.l.",
    "supporto": "Architettonico",
    "zone": [
      "Murature"
    ],
    "materials_used": [
      "Laterizio/cotto/mattoni"
    ],
    "technique_used": [],
    "environmental_issue": [],
    "working_issue": [],
    "observations": [
      "Sostituzione di laterizi rotti con altri di recupero dello stesso colore e dimensioni."
    ]
  },
  {
    "record_id": "1747",
    "Cantiere": "Cantiere di restauro: I stralcio - Messa di sicurezza dei locali di proprietà della Provincia dati in comodato ad Alma, Architettonico",
    "zone/subject_raw": "",
    "Date": "2013-05-03 00:00:00",
    "Author": "Buia Nereo S.r.l.",
    "supporto": "Architettonico",
    "zone": [
      "Murature"
    ],
    "materials_used": [
      "Calce idraulica / NHL"
    ],
    "technique_used": [
      "Interventi strutturali locali (cuci-scuci, cerchiatura, ancoraggi)"
    ],
    "environmental_issue": [],
    "working_issue": [],
    "observations": [
      "Rimontaggio della muratura e formazione di ammorsature, spigoli, riseghe con malta di calce idraulica NHL5."
    ]
  },
  {
    "record_id": "1747",
    "Cantiere": "Cantiere di restauro: I stralcio - Messa di sicurezza dei locali di proprietà della Provincia dati in comodato ad Alma, Architettonico",
    "zone/subject_raw": "",
    "Date": "2013-05-01 00:00:00",
    "Author": "Buia Nereo S.r.l.",
    "supporto": "Architettonico",
    "zone": [
      "Murature"
    ],
    "materials_used": [],
    "technique_used": [
      "Indagini diagnostiche e analisi preliminari"
    ],
    "environmental_issue": [],
    "working_issue": [],
    "observations": [
      "Ispezione della struttura portante e del rivestimento in malta di calce effettuata."
    ]
  },
  {
    "record_id": "1747",
    "Cantiere": "Cantiere di restauro: I stralcio - Messa di sicurezza dei locali di proprietà della Provincia dati in comodato ad Alma, Architettonico",
    "zone/subject_raw": "",
    "Date": "2013-05-01 00:00:00",
    "Author": "Buia Nereo S.r.l.",
    "supporto": "Architettonico",
    "zone": [],
    "materials_used": [],
    "technique_used": [],
    "environmental_issue": [],
    "working_issue": [],
    "observations": [
      "Eliminazione di tratti ammalorati, ma specifiche zone, materiali, tecniche o problemi non menzionati."
    ]
  },
  {
    "record_id": "1747",
    "Cantiere": "Cantiere di restauro: I stralcio - Messa di sicurezza dei locali di proprietà della Provincia dati in comodato ad Alma, Architettonico",
    "zone/subject_raw": "",
    "Date": "2013-05-01 00:00:00",
    "Author": "Buia Nereo S.r.l.",
    "supporto": "Architettonico",
    "zone": [
      "Murature"
    ],
    "materials_used": [
      "Laterizio/cotto/mattoni"
    ],
    "technique_used": [],
    "environmental_issue": [],
    "working_issue": [],
    "observations": [
      "Ripresa dei tratti di ossatura mancanti con mattoni di recupero."
    ]
  },
  {
    "record_id": "1747",
    "Cantiere": "Cantiere di restauro: I stralcio - Messa di sicurezza dei locali di proprietà della Provincia dati in comodato ad Alma, Architettonico",
    "zone/subject_raw": "",
    "Date": "2013-05-01 00:00:00",
    "Author": "Buia Nereo S.r.l.",
    "supporto": "Architettonico",
    "zone": [],
    "materials_used": [
      "Calce idraulica / NHL"
    ],
    "technique_used": [
      "Stuccatura / integrazione con malte"
    ],
    "environmental_issue": [],
    "working_issue": [],
    "observations": [
      "Applicazione della malta di calce idraulica tipo TCS."
    ]
  },
  {
    "record_id": "1747",
    "Cantiere": "Cantiere di restauro: I stralcio - Messa di sicurezza dei locali di proprietà della Provincia dati in comodato ad Alma, Architettonico",
    "zone/subject_raw": "",
    "Date": "2013-05-01 00:00:00",
    "Author": "Buia Nereo S.r.l.",
    "supporto": "",
    "zone": [],
    "materials_used": [],
    "technique_used": [],
    "environmental_issue": [],
    "working_issue": [],
    "observations": [
      "Non sono state fornite informazioni specifiche sui materiali utilizzati, sulle tecniche applicate o su eventuali problemi riscontrati."
    ]
  },
  {
    "record_id": "1747",
    "Cantiere": "Cantiere di restauro: I stralcio - Messa di sicurezza dei locali di proprietà della Provincia dati in comodato ad Alma, Architettonico",
    "zone/subject_raw": "",
    "Date": "2013-06-01 00:00:00",
    "Author": "Buia Nereo S.r.l.",
    "supporto": "Architettonico",
    "zone": [],
    "materials_used": [
      "Malte cementizie",
      "Calce idraulica / NHL"
    ],
    "technique_used": [
      "Interventi su intonaci (intonacatura / reintonacatura)"
    ],
    "environmental_issue": [],
    "working_issue": [],
    "observations": [
      "Stesura di intonaco a malta di calce idraulica, a due mani, per l'applicazione di strato finale."
    ]
  },
  {
    "record_id": "1747",
    "Cantiere": "Cantiere di restauro: I stralcio - Messa di sicurezza dei locali di proprietà della Provincia dati in comodato ad Alma, Architettonico",
    "zone/subject_raw": "",
    "Date": "2013-06-01 00:00:00",
    "Author": "Buia Nereo S.r.l.",
    "supporto": "Architettonico",
    "zone": [],
    "materials_used": [
      "Malte cementizie"
    ],
    "technique_used": [
      "Interventi su intonaci (intonacatura / reintonacatura)"
    ],
    "environmental_issue": [],
    "working_issue": [],
    "observations": [
      "Strato finale di intonaco realizzato a malta di calce idraulica, finito a spugna."
    ]
  },
  {
    "record_id": "1747",
    "Cantiere": "Cantiere di restauro: I stralcio - Messa di sicurezza dei locali di proprietà della Provincia dati in comodato ad Alma, Architettonico",
    "zone/subject_raw": "",
    "Date": "2013-06-01 00:00:00",
    "Author": "Buia Nereo S.r.l.",
    "supporto": "Architettonico",
    "zone": [],
    "materials_used": [
      "Calce (grassello, calce dolce, calce storica)"
    ],
    "technique_used": [
      "Ritocco / velatura / patinatura"
    ],
    "environmental_issue": [],
    "working_issue": [],
    "observations": [
      "Velatura finale eseguita con calce stesa a tre mani, con la prima mano applicata su un intonachino bagnato."
    ]
  },
  {
    "record_id": "1747",
    "Cantiere": "Cantiere di restauro: I stralcio - Messa di sicurezza dei locali di proprietà della Provincia dati in comodato ad Alma, Architettonico",
    "zone/subject_raw": "Secondo piano e soppalchi-ala sud",
    "Date": "2013-04-01 00:00:00",
    "Author": "Buia Nereo S.r.l.",
    "supporto": "Murario",
    "zone": [
      "Murature"
    ],
    "materials_used": [
      "Fibre e compositi (fibra di vetro, carbonio, vetroresina)"
    ],
    "technique_used": [
      "Interventi strutturali locali (cuci-scuci, cerchiatura, ancoraggi)"
    ],
    "environmental_issue": [],
    "working_issue": [],
    "observations": [
      "Inserimento di un tutore solidarizzato alla struttura muraria tramite fibre composite al carbonio e fiberglass."
    ]
  },
  {
    "record_id": "1747",
    "Cantiere": "Cantiere di restauro: I stralcio - Messa di sicurezza dei locali di proprietà della Provincia dati in comodato ad Alma, Architettonico",
    "zone/subject_raw": "",
    "Date": "2013-04-01 00:00:00",
    "Author": "Buia Nereo S.r.l.",
    "supporto": "Architettonico",
    "zone": [
      "Pavimenti/Solai"
    ],
    "materials_used": [
      "Cemento/calcestruzzo/cementite",
      "Ferramenta e fissaggi (chiodi, viti, bulloni, tasselli, staffe)",
      "Metalli ferrosi (ferro, acciaio, zincato)"
    ],
    "technique_used": [
      "Consolidamento per iniezione / impregnazione"
    ],
    "environmental_issue": [],
    "working_issue": [],
    "observations": [
      "Consolidamento dei solai in legno con uso di materiali metallici e cementizi."
    ]
  },
  {
    "record_id": "1747",
    "Cantiere": "Cantiere di restauro: I stralcio - Messa di sicurezza dei locali di proprietà della Provincia dati in comodato ad Alma, Architettonico",
    "zone/subject_raw": "",
    "Date": "2013-04-01 00:00:00",
    "Author": "Buia Nereo S.r.l.",
    "supporto": "Architettonico",
    "zone": [],
    "materials_used": [
      "Fibre e compositi (fibra di vetro, carbonio, vetroresina)"
    ],
    "technique_used": [
      "Interventi strutturali locali (cuci-scuci, cerchiatura, ancoraggi)"
    ],
    "environmental_issue": [],
    "working_issue": [],
    "observations": [
      "Placcaggio di copertura con tessuto in fibra di carbonio nel sottotetto"
    ]
  },
  {
    "record_id": "1747",
    "Cantiere": "Cantiere di restauro: I stralcio - Messa di sicurezza dei locali di proprietà della Provincia dati in comodato ad Alma, Architettonico",
    "zone/subject_raw": "",
    "Date": "2013-04-01 00:00:00",
    "Author": "Buia Nereo S.r.l.",
    "supporto": "Architettonico",
    "zone": [],
    "materials_used": [
      "Tessuti e TNT (lino, tela, teli TNT, geotessili, garze)",
      "Fibre e compositi (fibra di vetro, carbonio, vetroresina)"
    ],
    "technique_used": [
      "Interventi strutturali locali (cuci-scuci, cerchiatura, ancoraggi)"
    ],
    "environmental_issue": [],
    "working_issue": [],
    "observations": [
      "Il testo menziona l'utilizzo di tessuto in fibra di carbonio per la cerchiatura."
    ]
  }
]